[
	{
		"id":"21009", 
		"name":"Doom Trooper", 
		"title":"", 
		"isRaid":"false", 
		"isGrandBoss":"false", 
		"drops":[{"id":"358", "min":"1", "max":"1", "chance":"9"}, {"id":"2380", "min":"1", "max":"1", "chance":"14"}, {"id":"2381", "min":"1", "max":"1", "chance":"6"}, {"id":"1865", "min":"1", "max":"1", "chance":"90909"}, {"id":"1870", "min":"1", "max":"1", "chance":"90909"}, {"id":"1875", "min":"1", "max":"1", "chance":"7752"}, {"id":"1879", "min":"1", "max":"1", "chance":"15873"}, {"id":"4040", "min":"1", "max":"1", "chance":"2169"}, {"id":"4078", "min":"1", "max":"1", "chance":"1921"}, {"id":"4080", "min":"1", "max":"1", "chance":"2705"}, {"id":"4081", "min":"1", "max":"1", "chance":"1296"}, {"id":"5004", "min":"1", "max":"1", "chance":"86"}, {"id":"5281", "min":"1", "max":"1", "chance":"151"}, {"id":"8729", "min":"1", "max":"1", "chance":"1116"}, {"id":"8739", "min":"1", "max":"1", "chance":"279"}, {"id":"8759", "min":"1", "max":"1", "chance":"93"}, {"id":"57", "min":"1080", "max":"2188", "chance":"700000"}, {"id":"948", "min":"1", "max":"1", "chance":"6677"}, {"id":"4052", "min":"1", "max":"1", "chance":"94558"}, {"id":"4104", "min":"1", "max":"1", "chance":"15284"}],
		"skills":[{"id":"4072", "level":"6"}, {"id":"4091", "level":"1"}, {"id":"4244", "level":"6"}, {"id":"4275", "level":"2"}, {"id":"4278", "level":"1"}, {"id":"4410", "level":"12"}, {"id":"4411", "level":"12"}, {"id":"4412", "level":"10"}, {"id":"4413", "level":"10"}]
	}
]