[
    {
        "id": "22021",
        "name": "Bandit Undertaker",
        "title": "",
        "isRaid": "false",
        "isGrandBoss": "false",
        "drops": [
            {
                "id": "157",
                "min": "1",
                "max": "1",
                "chance": "8"
            },
            {
                "id": "186",
                "min": "1",
                "max": "1",
                "chance": "8"
            },
            {
                "id": "1341",
                "min": "10",
                "max": "30",
                "chance": "166667"
            },
            {
                "id": "1874",
                "min": "1",
                "max": "1",
                "chance": "4115"
            },
            {
                "id": "1878",
                "min": "1",
                "max": "1",
                "chance": "16393"
            },
            {
                "id": "1884",
                "min": "1",
                "max": "1",
                "chance": "29412"
            },
            {
                "id": "1889",
                "min": "1",
                "max": "1",
                "chance": "1028"
            },
            {
                "id": "2027",
                "min": "1",
                "max": "1",
                "chance": "1912"
            },
            {
                "id": "5220",
                "min": "1",
                "max": "1",
                "chance": "1057"
            },
            {
                "id": "8295",
                "min": "1",
                "max": "1",
                "chance": "805"
            },
            {
                "id": "57",
                "min": "291",
                "max": "580",
                "chance": "700000"
            },
            {
                "id": "1874",
                "min": "1",
                "max": "1",
                "chance": "50000"
            },
            {
                "id": "1939",
                "min": "1",
                "max": "1",
                "chance": "25000"
            },
            {
                "id": "5220",
                "min": "1",
                "max": "1",
                "chance": "50000"
            }
        ],
        "skills": [
            {
                "id": "4151",
                "level": "1"
            },
            {
                "id": "4160",
                "level": "1"
            },
            {
                "id": "4274",
                "level": "2"
            },
            {
                "id": "4412",
                "level": "12"
            },
            {
                "id": "4450",
                "level": "3"
            }
        ]
    }
]